[
    [
        {
            "id": "3dc27ac7-285a-4497-93e3-b545b33188a3",
            "wname": "Basic Staff",
            "wtype": "Normal",
            "slots": 4,
            "slot_link": 2,
            "damage": 10,
            "is_unique": "Abigail",
            "is_avail": true
        }
    ],
    [
        {
            "id": "8db5530d-3a37-428a-925c-4c09aa3ce93d",
            "aname": "Basic Leather",
            "atype": "Normal",
            "slots": 3,
            "slot_link": 1,
            "physmit": 10,
            "techmit": 15,
            "is_avail": true
        }
    ],
    [
        {
            "id": "f69f116d-ea13-41f5-887b-e5dd1079e531",
            "uname": "Compact Cell",
            "utype": "Superconductor",
            "boon": "Energy Producing",
            "mastery": 1,
            "mastered_boon": "Techs Iterate Twice",
            "mboon_avail": false,
            "is_avail": true
        }
    ]
]